{
  "updated_at": "2026-01-29 17:12:55",
  "market_status": "open",
  "signals": {
    "tier_up": [],
    "tier_down": [],
    "rank_up_major": [
      {
        "ticker": "PCG",
        "name": "PG&E",
        "price": 15.06,
        "change": 0.9,
        "tier": 2,
        "rank": 56,
        "diff": 33
      },
      {
        "ticker": "AMZN",
        "name": "아마존",
        "price": 239.15,
        "change": -1.59,
        "tier": 2,
        "rank": 81,
        "diff": 32
      },
      {
        "ticker": "GPN",
        "name": "글로벌 페이먼츠",
        "price": 71.51,
        "change": -0.69,
        "tier": 2,
        "rank": 90,
        "diff": 31
      },
      {
        "ticker": "DIS",
        "name": "월트 디즈니",
        "price": 110.72,
        "change": 1.06,
        "tier": 3,
        "rank": 103,
        "diff": 37
      },
      {
        "ticker": "URI",
        "name": "유나이티드 렌탈스",
        "price": 767.03,
        "change": -15.08,
        "tier": 3,
        "rank": 109,
        "diff": 109
      },
      {
        "ticker": "CTSH",
        "name": "코그니전트 테크놀로지 솔루션즈",
        "price": 82.5,
        "change": -0.96,
        "tier": 3,
        "rank": 111,
        "diff": 34
      },
      {
        "ticker": "ADSK",
        "name": "오토데스크",
        "price": 254.54,
        "change": -5.14,
        "tier": 3,
        "rank": 125,
        "diff": 48
      },
      {
        "ticker": "GDDY",
        "name": "고대디",
        "price": 99.71,
        "change": -3.53,
        "tier": 3,
        "rank": 136,
        "diff": 34
      },
      {
        "ticker": "EBAY",
        "name": "이베이",
        "price": 94.65,
        "change": -0.54,
        "tier": 3,
        "rank": 137,
        "diff": 35
      },
      {
        "ticker": "WEC",
        "name": "WEC 에너지 그룹",
        "price": 110.46,
        "change": 0.38,
        "tier": 3,
        "rank": 148,
        "diff": 60
      },
      {
        "ticker": "NFLX",
        "name": "넷플릭스",
        "price": 82.61,
        "change": -2.4,
        "tier": 3,
        "rank": 150,
        "diff": 31
      },
      {
        "ticker": "LULU",
        "name": "룰루레몬 애슬레티카",
        "price": 174.87,
        "change": -3.04,
        "tier": 3,
        "rank": 151,
        "diff": 41
      },
      {
        "ticker": "INVH",
        "name": "인비테이션 홈즈",
        "price": 26.42,
        "change": 0.8,
        "tier": 3,
        "rank": 155,
        "diff": 67
      },
      {
        "ticker": "OMC",
        "name": "옴니콤 그룹",
        "price": 75.62,
        "change": -1.2,
        "tier": 3,
        "rank": 159,
        "diff": 58
      },
      {
        "ticker": "AVB",
        "name": "아발론베이 커뮤니티스",
        "price": 175.08,
        "change": 1.22,
        "tier": 3,
        "rank": 161,
        "diff": 53
      },
      {
        "ticker": "COP",
        "name": "코노코필립스",
        "price": 104.63,
        "change": 3.2,
        "tier": 3,
        "rank": 162,
        "diff": 37
      },
      {
        "ticker": "WYNN",
        "name": "윈 리조트",
        "price": 108.99,
        "change": -3.45,
        "tier": 3,
        "rank": 164,
        "diff": 47
      },
      {
        "ticker": "LHX",
        "name": "L3해리스 테크놀로지스",
        "price": 353.93,
        "change": -1.77,
        "tier": 3,
        "rank": 167,
        "diff": 53
      },
      {
        "ticker": "KIM",
        "name": "킴코 리얼티",
        "price": 20.67,
        "change": 0.9,
        "tier": 3,
        "rank": 178,
        "diff": 32
      },
      {
        "ticker": "TKO",
        "name": "TKO 그룹 홀딩스",
        "price": 195.77,
        "change": 0.46,
        "tier": 3,
        "rank": 184,
        "diff": 41
      },
      {
        "ticker": "MO",
        "name": "알트리아 그룹",
        "price": 61.47,
        "change": -2.64,
        "tier": 3,
        "rank": 191,
        "diff": 32
      },
      {
        "ticker": "AMD",
        "name": "AMD",
        "price": 245.87,
        "change": -2.72,
        "tier": 3,
        "rank": 193,
        "diff": 68
      },
      {
        "ticker": "GEHC",
        "name": "GE 헬스케어",
        "price": 78.04,
        "change": -1.54,
        "tier": 3,
        "rank": 195,
        "diff": 60
      },
      {
        "ticker": "HOLX",
        "name": "홀로직",
        "price": 75.03,
        "change": -0.09,
        "tier": 3,
        "rank": 200,
        "diff": 47
      },
      {
        "ticker": "WM",
        "name": "웨이스트 매니지먼트",
        "price": 226.49,
        "change": -2.21,
        "tier": 3,
        "rank": 208,
        "diff": 49
      },
      {
        "ticker": "GRMN",
        "name": "가민",
        "price": 201.87,
        "change": -1.28,
        "tier": 3,
        "rank": 212,
        "diff": 41
      },
      {
        "ticker": "ACN",
        "name": "액센츄어",
        "price": 262.11,
        "change": -3.07,
        "tier": 3,
        "rank": 221,
        "diff": 74
      },
      {
        "ticker": "PG",
        "name": "P&G",
        "price": 150.0,
        "change": 1.81,
        "tier": 3,
        "rank": 222,
        "diff": 43
      },
      {
        "ticker": "CAT",
        "name": "캐터필러",
        "price": 669.58,
        "change": 4.09,
        "tier": 3,
        "rank": 226,
        "diff": 32
      },
      {
        "ticker": "XOM",
        "name": "엑슨 모빌",
        "price": 139.65,
        "change": 1.5,
        "tier": 3,
        "rank": 235,
        "diff": 73
      },
      {
        "ticker": "FAST",
        "name": "패스널",
        "price": 43.51,
        "change": -0.24,
        "tier": 3,
        "rank": 242,
        "diff": 59
      },
      {
        "ticker": "GS",
        "name": "골드만삭스 그룹",
        "price": 931.82,
        "change": -0.53,
        "tier": 3,
        "rank": 250,
        "diff": 56
      },
      {
        "ticker": "TSCO",
        "name": "트랙터 서플라이",
        "price": 51.61,
        "change": -6.4,
        "tier": 4,
        "rank": 265,
        "diff": 34
      },
      {
        "ticker": "WAT",
        "name": "워터스",
        "price": 376.47,
        "change": -2.22,
        "tier": 4,
        "rank": 271,
        "diff": 50
      },
      {
        "ticker": "CDNS",
        "name": "케이던스 디자인 시스템즈",
        "price": 298.95,
        "change": -6.72,
        "tier": 4,
        "rank": 276,
        "diff": 39
      },
      {
        "ticker": "ETR",
        "name": "엔터지",
        "price": 96.54,
        "change": 0.07,
        "tier": 4,
        "rank": 282,
        "diff": 48
      },
      {
        "ticker": "TMO",
        "name": "써모 피셔 사이언티픽",
        "price": 595.35,
        "change": -2.08,
        "tier": 4,
        "rank": 288,
        "diff": 35
      },
      {
        "ticker": "CMI",
        "name": "커민스",
        "price": 583.59,
        "change": 0.99,
        "tier": 4,
        "rank": 301,
        "diff": 38
      },
      {
        "ticker": "HLT",
        "name": "힐튼 월드와이드 홀딩스",
        "price": 300.43,
        "change": 1.39,
        "tier": 4,
        "rank": 302,
        "diff": 45
      },
      {
        "ticker": "LMT",
        "name": "록히드 마틴",
        "price": 632.46,
        "change": 5.89,
        "tier": 4,
        "rank": 323,
        "diff": 69
      },
      {
        "ticker": "TYL",
        "name": "타일러 테크놀로지스",
        "price": 390.48,
        "change": -6.83,
        "tier": 4,
        "rank": 349,
        "diff": 36
      },
      {
        "ticker": "VLO",
        "name": "발레로 에너지",
        "price": 190.57,
        "change": 3.56,
        "tier": 4,
        "rank": 352,
        "diff": 37
      },
      {
        "ticker": "DTE",
        "name": "DTE 에너지",
        "price": 136.98,
        "change": 0.3,
        "tier": 4,
        "rank": 359,
        "diff": 32
      },
      {
        "ticker": "MTD",
        "name": "메틀러 톨레도 인터내셔널",
        "price": 1387.68,
        "change": -1.0,
        "tier": 4,
        "rank": 364,
        "diff": 31
      },
      {
        "ticker": "PANW",
        "name": "팔로알토 네트웍스",
        "price": 172.62,
        "change": -6.05,
        "tier": 4,
        "rank": 365,
        "diff": 48
      },
      {
        "ticker": "FTNT",
        "name": "포티넷",
        "price": 80.39,
        "change": -2.06,
        "tier": 4,
        "rank": 373,
        "diff": 41
      },
      {
        "ticker": "FDS",
        "name": "팩트셋 리서치 시스템즈",
        "price": 255.23,
        "change": -5.42,
        "tier": 4,
        "rank": 396,
        "diff": 32
      }
    ],
    "rank_down_major": [
      {
        "ticker": "PNC",
        "name": "PNC 파이낸셜 서비시스 그룹",
        "price": 222.45,
        "change": 0.48,
        "tier": 2,
        "rank": 84,
        "diff": -37
      },
      {
        "ticker": "SPG",
        "name": "사이먼 프로퍼티 그룹",
        "price": 187.12,
        "change": 1.83,
        "tier": 3,
        "rank": 113,
        "diff": -36
      },
      {
        "ticker": "HCA",
        "name": "HCA 헬스케어",
        "price": 485.97,
        "change": -1.07,
        "tier": 3,
        "rank": 118,
        "diff": -39
      },
      {
        "ticker": "IVZ",
        "name": "인베스코",
        "price": 27.56,
        "change": 0.0,
        "tier": 3,
        "rank": 128,
        "diff": -32
      },
      {
        "ticker": "TT",
        "name": "트레인 테크놀로지스",
        "price": 426.78,
        "change": 8.26,
        "tier": 3,
        "rank": 144,
        "diff": -45
      },
      {
        "ticker": "SWKS",
        "name": "스카이웍스 솔루션즈",
        "price": 55.7,
        "change": 0.76,
        "tier": 3,
        "rank": 147,
        "diff": -33
      },
      {
        "ticker": "ATO",
        "name": "애트모스 에너지",
        "price": 166.87,
        "change": 0.52,
        "tier": 3,
        "rank": 154,
        "diff": -50
      },
      {
        "ticker": "XYL",
        "name": "자일럼",
        "price": 136.51,
        "change": 0.73,
        "tier": 3,
        "rank": 169,
        "diff": -34
      },
      {
        "ticker": "T",
        "name": "AT&T",
        "price": 24.82,
        "change": 3.1,
        "tier": 3,
        "rank": 177,
        "diff": -35
      },
      {
        "ticker": "RCL",
        "name": "로얄 캐리비안 크루즈",
        "price": 335.17,
        "change": 14.94,
        "tier": 3,
        "rank": 180,
        "diff": -95
      },
      {
        "ticker": "JBHT",
        "name": "JB 헌트 트랜스포트 서비시스",
        "price": 205.69,
        "change": 0.31,
        "tier": 3,
        "rank": 210,
        "diff": -46
      },
      {
        "ticker": "MKC",
        "name": "맥코믹 앤 컴퍼니",
        "price": 61.67,
        "change": -0.31,
        "tier": 3,
        "rank": 211,
        "diff": -60
      },
      {
        "ticker": "PAYX",
        "name": "페이첵스",
        "price": 102.94,
        "change": 0.48,
        "tier": 3,
        "rank": 219,
        "diff": -32
      },
      {
        "ticker": "EXPD",
        "name": "익스피다이터스 인터내셔널 오브 워싱턴",
        "price": 162.14,
        "change": 1.29,
        "tier": 3,
        "rank": 228,
        "diff": -31
      },
      {
        "ticker": "REG",
        "name": "리젠시 센터스",
        "price": 71.65,
        "change": 1.7,
        "tier": 3,
        "rank": 230,
        "diff": -59
      },
      {
        "ticker": "META",
        "name": "메타 플랫폼스(페이스북)",
        "price": 728.62,
        "change": 8.96,
        "tier": 3,
        "rank": 231,
        "diff": -45
      },
      {
        "ticker": "COF",
        "name": "캐피털 원 파이낸셜",
        "price": 219.09,
        "change": 0.31,
        "tier": 3,
        "rank": 237,
        "diff": -60
      },
      {
        "ticker": "NCLH",
        "name": "노르웨이지안 크루즈 라인 홀딩스",
        "price": 22.75,
        "change": 9.43,
        "tier": 3,
        "rank": 240,
        "diff": -38
      },
      {
        "ticker": "EQT",
        "name": "EQT",
        "price": 56.53,
        "change": 1.02,
        "tier": 3,
        "rank": 245,
        "diff": -36
      },
      {
        "ticker": "UPS",
        "name": "유나이티드 파셀 서비스",
        "price": 105.81,
        "change": 2.03,
        "tier": 4,
        "rank": 251,
        "diff": -47
      },
      {
        "ticker": "DPZ",
        "name": "도미노 피자",
        "price": 410.35,
        "change": 1.23,
        "tier": 4,
        "rank": 261,
        "diff": -70
      },
      {
        "ticker": "HUBB",
        "name": "허벨",
        "price": 492.43,
        "change": 1.38,
        "tier": 4,
        "rank": 263,
        "diff": -102
      },
      {
        "ticker": "CSX",
        "name": "CSX",
        "price": 37.46,
        "change": 0.21,
        "tier": 4,
        "rank": 274,
        "diff": -30
      },
      {
        "ticker": "NWSA",
        "name": "뉴스 코퍼레이션 A",
        "price": 26.49,
        "change": -0.39,
        "tier": 4,
        "rank": 277,
        "diff": -77
      },
      {
        "ticker": "TDY",
        "name": "텔레다인 테크놀로지스",
        "price": 621.55,
        "change": 0.2,
        "tier": 4,
        "rank": 278,
        "diff": -36
      },
      {
        "ticker": "FFIV",
        "name": "F5",
        "price": 277.74,
        "change": -4.98,
        "tier": 4,
        "rank": 283,
        "diff": -34
      },
      {
        "ticker": "PODD",
        "name": "인슐릿",
        "price": 255.51,
        "change": -1.04,
        "tier": 4,
        "rank": 284,
        "diff": -38
      },
      {
        "ticker": "LII",
        "name": "레녹스 인터내셔널",
        "price": 492.92,
        "change": 1.11,
        "tier": 4,
        "rank": 289,
        "diff": -30
      },
      {
        "ticker": "HUM",
        "name": "휴매나",
        "price": 194.65,
        "change": 0.33,
        "tier": 4,
        "rank": 299,
        "diff": -48
      },
      {
        "ticker": "PRU",
        "name": "푸르덴셜 파이낸셜",
        "price": 109.36,
        "change": 1.56,
        "tier": 4,
        "rank": 312,
        "diff": -37
      },
      {
        "ticker": "PPG",
        "name": "PPG 인더스트리스",
        "price": 115.65,
        "change": 1.48,
        "tier": 4,
        "rank": 313,
        "diff": -34
      },
      {
        "ticker": "PLD",
        "name": "프로로지스",
        "price": 129.72,
        "change": 2.04,
        "tier": 4,
        "rank": 315,
        "diff": -49
      },
      {
        "ticker": "NI",
        "name": "나이소스 에너지",
        "price": 44.42,
        "change": 0.19,
        "tier": 4,
        "rank": 316,
        "diff": -44
      },
      {
        "ticker": "BG",
        "name": "번지 글로벌",
        "price": 115.15,
        "change": -0.13,
        "tier": 4,
        "rank": 332,
        "diff": -36
      },
      {
        "ticker": "GPC",
        "name": "제뉴인 파츠",
        "price": 139.39,
        "change": -0.45,
        "tier": 4,
        "rank": 353,
        "diff": -34
      },
      {
        "ticker": "APTV",
        "name": "앱티브",
        "price": 78.41,
        "change": 0.77,
        "tier": 4,
        "rank": 356,
        "diff": -42
      },
      {
        "ticker": "MRSH",
        "name": "마시 앤드 맥레넌",
        "price": 185.65,
        "change": 4.19,
        "tier": 4,
        "rank": 357,
        "diff": -39
      },
      {
        "ticker": "CVS",
        "name": "CVS 헬스",
        "price": 74.31,
        "change": 0.37,
        "tier": 4,
        "rank": 358,
        "diff": -41
      },
      {
        "ticker": "AMT",
        "name": "아메리칸 타워",
        "price": 179.14,
        "change": 0.92,
        "tier": 4,
        "rank": 368,
        "diff": -44
      },
      {
        "ticker": "MSI",
        "name": "모토로라 솔루션즈",
        "price": 399.86,
        "change": -1.29,
        "tier": 4,
        "rank": 369,
        "diff": -41
      },
      {
        "ticker": "HSIC",
        "name": "헨리 셰인",
        "price": 74.85,
        "change": -0.31,
        "tier": 4,
        "rank": 382,
        "diff": -41
      },
      {
        "ticker": "GM",
        "name": "제너럴 모터스",
        "price": 86.18,
        "change": 1.51,
        "tier": 4,
        "rank": 388,
        "diff": -31
      },
      {
        "ticker": "KEYS",
        "name": "키사이트 테크놀로지스",
        "price": 221.2,
        "change": -0.14,
        "tier": 4,
        "rank": 400,
        "diff": -30
      },
      {
        "ticker": "MSCI",
        "name": "MSCI",
        "price": 605.83,
        "change": -1.47,
        "tier": 5,
        "rank": 413,
        "diff": -37
      },
      {
        "ticker": "MOH",
        "name": "몰리나 헬스케어",
        "price": 186.43,
        "change": -0.3,
        "tier": 5,
        "rank": 415,
        "diff": -43
      },
      {
        "ticker": "BBY",
        "name": "베스트 바이",
        "price": 65.78,
        "change": 0.34,
        "tier": 5,
        "rank": 430,
        "diff": -43
      }
    ],
    "new_tier_1": [],
    "golden_cross": [
      {
        "ticker": "VZ",
        "name": "버라이즌 커뮤니케이션스",
        "price": 39.96,
        "change": 1.38,
        "tier": 1,
        "rank": 21
      },
      {
        "ticker": "STLD",
        "name": "스틸 다이내믹스",
        "price": 179.57,
        "change": 2.98,
        "tier": 2,
        "rank": 44
      },
      {
        "ticker": "EQR",
        "name": "에퀴티 레지덴셜",
        "price": 61.9,
        "change": 1.88,
        "tier": 2,
        "rank": 49
      },
      {
        "ticker": "AOS",
        "name": "A O 스미스",
        "price": 73.96,
        "change": 6.44,
        "tier": 2,
        "rank": 61
      },
      {
        "ticker": "SPG",
        "name": "사이먼 프로퍼티 그룹",
        "price": 187.12,
        "change": 1.83,
        "tier": 3,
        "rank": 113
      },
      {
        "ticker": "AIG",
        "name": "아메리칸 인터내셔널 그룹",
        "price": 73.73,
        "change": 0.46,
        "tier": 3,
        "rank": 158
      },
      {
        "ticker": "FICO",
        "name": "페어 아이작",
        "price": 1563.0,
        "change": 2.45,
        "tier": 3,
        "rank": 175
      },
      {
        "ticker": "RCL",
        "name": "로얄 캐리비안 크루즈",
        "price": 335.17,
        "change": 14.94,
        "tier": 3,
        "rank": 180
      },
      {
        "ticker": "MTB",
        "name": "M&T 뱅크",
        "price": 219.73,
        "change": 1.31,
        "tier": 3,
        "rank": 197
      },
      {
        "ticker": "NSC",
        "name": "노퍽 서던",
        "price": 288.76,
        "change": 1.51,
        "tier": 3,
        "rank": 215
      },
      {
        "ticker": "CAT",
        "name": "캐터필러",
        "price": 669.58,
        "change": 4.09,
        "tier": 3,
        "rank": 226
      },
      {
        "ticker": "AFL",
        "name": "애플랙",
        "price": 110.34,
        "change": 1.3,
        "tier": 3,
        "rank": 241
      },
      {
        "ticker": "TMUS",
        "name": "T 모바일 US",
        "price": 188.16,
        "change": 1.03,
        "tier": 4,
        "rank": 258
      },
      {
        "ticker": "IBM",
        "name": "IBM",
        "price": 311.77,
        "change": 5.98,
        "tier": 4,
        "rank": 336
      },
      {
        "ticker": "VLO",
        "name": "발레로 에너지",
        "price": 190.57,
        "change": 3.56,
        "tier": 4,
        "rank": 352
      },
      {
        "ticker": "HPE",
        "name": "휴렛 패커드 엔터프라이즈",
        "price": 21.77,
        "change": 0.28,
        "tier": 4,
        "rank": 381
      },
      {
        "ticker": "ROK",
        "name": "로크웰 오토메이션",
        "price": 426.52,
        "change": 2.8,
        "tier": 5,
        "rank": 409
      },
      {
        "ticker": "BBY",
        "name": "베스트 바이",
        "price": 65.78,
        "change": 0.34,
        "tier": 5,
        "rank": 430
      },
      {
        "ticker": "WRB",
        "name": "WR 버클리",
        "price": 68.18,
        "change": 0.75,
        "tier": 5,
        "rank": 431
      }
    ],
    "dead_cross": [],
    "rsi_overbought": [
      {
        "ticker": "NEM",
        "name": "뉴몬트",
        "price": 125.08,
        "change": -5.21,
        "tier": 1,
        "rank": 3,
        "rsi": 77.5
      },
      {
        "ticker": "MU",
        "name": "마이크론 테크놀로지",
        "price": 430.0,
        "change": -1.21,
        "tier": 1,
        "rank": 12,
        "rsi": 82.2
      },
      {
        "ticker": "CTRA",
        "name": "코테라 에너지",
        "price": 28.34,
        "change": 1.98,
        "tier": 1,
        "rank": 25,
        "rsi": 84.8
      },
      {
        "ticker": "JNJ",
        "name": "존슨 앤 존슨",
        "price": 227.29,
        "change": -0.19,
        "tier": 2,
        "rank": 27,
        "rsi": 88.1
      },
      {
        "ticker": "DVN",
        "name": "데번 에너지",
        "price": 40.44,
        "change": 1.53,
        "tier": 2,
        "rank": 41,
        "rsi": 75.4
      },
      {
        "ticker": "FANG",
        "name": "다이아몬드백 에너지",
        "price": 163.94,
        "change": 2.29,
        "tier": 2,
        "rank": 47,
        "rsi": 76.2
      },
      {
        "ticker": "HII",
        "name": "헌팅턴 잉걸스 인더스트리스",
        "price": 426.95,
        "change": 0.37,
        "tier": 2,
        "rank": 55,
        "rsi": 76.9
      },
      {
        "ticker": "AEE",
        "name": "애머런",
        "price": 103.65,
        "change": 0.07,
        "tier": 2,
        "rank": 59,
        "rsi": 72.8
      },
      {
        "ticker": "KO",
        "name": "코카콜라",
        "price": 73.71,
        "change": 0.88,
        "tier": 2,
        "rank": 73,
        "rsi": 76.3
      },
      {
        "ticker": "PEG",
        "name": "퍼블릭 서비스 엔터프라이즈 그룹",
        "price": 81.64,
        "change": 0.23,
        "tier": 2,
        "rank": 77,
        "rsi": 78.3
      },
      {
        "ticker": "LRCX",
        "name": "램 리서치",
        "price": 242.18,
        "change": 1.09,
        "tier": 2,
        "rank": 82,
        "rsi": 73.8
      },
      {
        "ticker": "GILD",
        "name": "길리어드 사이언스",
        "price": 139.13,
        "change": -0.42,
        "tier": 2,
        "rank": 83,
        "rsi": 79.8
      },
      {
        "ticker": "MPWR",
        "name": "모놀리식 파워 시스템즈",
        "price": 1160.86,
        "change": -0.08,
        "tier": 2,
        "rank": 88,
        "rsi": 93.9
      },
      {
        "ticker": "DUK",
        "name": "듀크 에너지",
        "price": 121.03,
        "change": 0.66,
        "tier": 2,
        "rank": 98,
        "rsi": 70.0
      },
      {
        "ticker": "OKE",
        "name": "원오크",
        "price": 80.19,
        "change": 1.17,
        "tier": 3,
        "rank": 112,
        "rsi": 74.4
      },
      {
        "ticker": "ANET",
        "name": "아리스타 네트웍스",
        "price": 148.19,
        "change": -1.31,
        "tier": 3,
        "rank": 120,
        "rsi": 74.2
      },
      {
        "ticker": "EME",
        "name": "엠코 그룹",
        "price": 733.03,
        "change": 0.78,
        "tier": 3,
        "rank": 121,
        "rsi": 79.9
      },
      {
        "ticker": "JCI",
        "name": "존슨 콘트롤즈 인터내셔널",
        "price": 119.92,
        "change": 2.72,
        "tier": 3,
        "rank": 123,
        "rsi": 81.2
      },
      {
        "ticker": "NOC",
        "name": "노스롭 그루먼",
        "price": 694.46,
        "change": 0.77,
        "tier": 3,
        "rank": 124,
        "rsi": 83.6
      },
      {
        "ticker": "FIX",
        "name": "컴포트 시스템즈 USA",
        "price": 1169.96,
        "change": 0.08,
        "tier": 3,
        "rank": 126,
        "rsi": 84.0
      },
      {
        "ticker": "HON",
        "name": "허니웰 인터내셔널",
        "price": 225.58,
        "change": 4.13,
        "tier": 3,
        "rank": 131,
        "rsi": 74.9
      },
      {
        "ticker": "CF",
        "name": "CF 인더스트리스 홀딩스",
        "price": 93.84,
        "change": 0.72,
        "tier": 3,
        "rank": 134,
        "rsi": 77.4
      },
      {
        "ticker": "CHRW",
        "name": "CH 로빈슨 월드와이드",
        "price": 191.2,
        "change": 3.76,
        "tier": 3,
        "rank": 138,
        "rsi": 86.8
      },
      {
        "ticker": "STX",
        "name": "씨게이트 테크놀로지",
        "price": 438.36,
        "change": -1.03,
        "tier": 3,
        "rank": 140,
        "rsi": 92.1
      },
      {
        "ticker": "AME",
        "name": "아메텍",
        "price": 225.3,
        "change": 1.27,
        "tier": 3,
        "rank": 141,
        "rsi": 77.7
      },
      {
        "ticker": "FCX",
        "name": "프리포트 맥모란",
        "price": 64.85,
        "change": 1.91,
        "tier": 3,
        "rank": 142,
        "rsi": 80.6
      },
      {
        "ticker": "TT",
        "name": "트레인 테크놀로지스",
        "price": 426.78,
        "change": 8.26,
        "tier": 3,
        "rank": 144,
        "rsi": 78.4
      },
      {
        "ticker": "WEC",
        "name": "WEC 에너지 그룹",
        "price": 110.46,
        "change": 0.38,
        "tier": 3,
        "rank": 148,
        "rsi": 83.3
      },
      {
        "ticker": "ROL",
        "name": "롤린스",
        "price": 62.73,
        "change": -0.16,
        "tier": 3,
        "rank": 166,
        "rsi": 75.9
      },
      {
        "ticker": "LHX",
        "name": "L3해리스 테크놀로지스",
        "price": 353.93,
        "change": -1.77,
        "tier": 3,
        "rank": 167,
        "rsi": 74.5
      },
      {
        "ticker": "KLAC",
        "name": "KLA",
        "price": 1646.98,
        "change": 1.22,
        "tier": 3,
        "rank": 170,
        "rsi": 79.8
      },
      {
        "ticker": "PM",
        "name": "필립 모리스 인터내셔널",
        "price": 178.63,
        "change": 0.02,
        "tier": 3,
        "rank": 187,
        "rsi": 79.8
      },
      {
        "ticker": "MO",
        "name": "알트리아 그룹",
        "price": 61.47,
        "change": -2.64,
        "tier": 3,
        "rank": 191,
        "rsi": 74.5
      },
      {
        "ticker": "AMD",
        "name": "AMD",
        "price": 245.87,
        "change": -2.72,
        "tier": 3,
        "rank": 193,
        "rsi": 77.6
      },
      {
        "ticker": "ED",
        "name": "컨솔리데이티드 에디슨",
        "price": 105.71,
        "change": 0.5,
        "tier": 3,
        "rank": 205,
        "rsi": 72.5
      },
      {
        "ticker": "NDSN",
        "name": "노드슨",
        "price": 272.06,
        "change": 0.04,
        "tier": 3,
        "rank": 207,
        "rsi": 73.0
      },
      {
        "ticker": "TRGP",
        "name": "타르가 리소시스",
        "price": 201.61,
        "change": 0.24,
        "tier": 3,
        "rank": 209,
        "rsi": 90.2
      },
      {
        "ticker": "PG",
        "name": "P&G",
        "price": 150.0,
        "change": 1.81,
        "tier": 3,
        "rank": 222,
        "rsi": 71.6
      },
      {
        "ticker": "CAT",
        "name": "캐터필러",
        "price": 669.58,
        "change": 4.09,
        "tier": 3,
        "rank": 226,
        "rsi": 71.7
      },
      {
        "ticker": "META",
        "name": "메타 플랫폼스(페이스북)",
        "price": 728.62,
        "change": 8.96,
        "tier": 3,
        "rank": 231,
        "rsi": 70.7
      },
      {
        "ticker": "IEX",
        "name": "아이덱스",
        "price": 197.5,
        "change": 0.56,
        "tier": 3,
        "rank": 233,
        "rsi": 72.4
      },
      {
        "ticker": "AMAT",
        "name": "어플라이드 머티어리얼즈",
        "price": 335.96,
        "change": -0.23,
        "tier": 3,
        "rank": 234,
        "rsi": 76.4
      },
      {
        "ticker": "XOM",
        "name": "엑슨 모빌",
        "price": 139.65,
        "change": 1.5,
        "tier": 3,
        "rank": 235,
        "rsi": 91.2
      },
      {
        "ticker": "FE",
        "name": "퍼스트에너지",
        "price": 47.4,
        "change": -0.02,
        "tier": 4,
        "rank": 254,
        "rsi": 78.2
      },
      {
        "ticker": "D",
        "name": "도미니언 에너지",
        "price": 60.81,
        "change": 0.16,
        "tier": 4,
        "rank": 267,
        "rsi": 71.8
      },
      {
        "ticker": "MDLZ",
        "name": "몬덜리즈 인터내셔널",
        "price": 57.78,
        "change": 0.09,
        "tier": 4,
        "rank": 268,
        "rsi": 73.4
      },
      {
        "ticker": "TDY",
        "name": "텔레다인 테크놀로지스",
        "price": 621.55,
        "change": 0.2,
        "tier": 4,
        "rank": 278,
        "rsi": 77.5
      },
      {
        "ticker": "KMI",
        "name": "킨더 모건",
        "price": 30.25,
        "change": 0.62,
        "tier": 4,
        "rank": 281,
        "rsi": 82.3
      },
      {
        "ticker": "ADM",
        "name": "아처 대니얼스 미들랜드",
        "price": 67.46,
        "change": 0.1,
        "tier": 4,
        "rank": 294,
        "rsi": 75.8
      },
      {
        "ticker": "CMI",
        "name": "커민스",
        "price": 583.59,
        "change": 0.99,
        "tier": 4,
        "rank": 301,
        "rsi": 70.3
      },
      {
        "ticker": "PPL",
        "name": "PPL",
        "price": 36.7,
        "change": -0.0,
        "tier": 4,
        "rank": 305,
        "rsi": 74.3
      },
      {
        "ticker": "EVRG",
        "name": "에버지",
        "price": 76.78,
        "change": 0.17,
        "tier": 4,
        "rank": 308,
        "rsi": 73.9
      },
      {
        "ticker": "PPG",
        "name": "PPG 인더스트리스",
        "price": 115.65,
        "change": 1.48,
        "tier": 4,
        "rank": 313,
        "rsi": 73.9
      },
      {
        "ticker": "NI",
        "name": "나이소스 에너지",
        "price": 44.42,
        "change": 0.19,
        "tier": 4,
        "rank": 316,
        "rsi": 79.8
      },
      {
        "ticker": "NEE",
        "name": "넥스트에라 에너지",
        "price": 88.21,
        "change": 0.73,
        "tier": 4,
        "rank": 320,
        "rsi": 96.0
      },
      {
        "ticker": "LMT",
        "name": "록히드 마틴",
        "price": 632.46,
        "change": 5.89,
        "tier": 4,
        "rank": 323,
        "rsi": 87.7
      },
      {
        "ticker": "SYY",
        "name": "시스코",
        "price": 83.68,
        "change": 0.2,
        "tier": 4,
        "rank": 324,
        "rsi": 75.9
      },
      {
        "ticker": "COR",
        "name": "센코라",
        "price": 355.24,
        "change": 1.34,
        "tier": 4,
        "rank": 327,
        "rsi": 74.3
      },
      {
        "ticker": "DLR",
        "name": "디지털 리얼티 트러스트",
        "price": 167.24,
        "change": 2.47,
        "tier": 4,
        "rank": 328,
        "rsi": 75.2
      },
      {
        "ticker": "ETN",
        "name": "이튼",
        "price": 353.17,
        "change": 1.68,
        "tier": 4,
        "rank": 331,
        "rsi": 76.8
      },
      {
        "ticker": "BG",
        "name": "번지 글로벌",
        "price": 115.15,
        "change": -0.13,
        "tier": 4,
        "rank": 332,
        "rsi": 90.7
      },
      {
        "ticker": "WDC",
        "name": "웨스턴 디지털",
        "price": 277.13,
        "change": -0.92,
        "tier": 4,
        "rank": 334,
        "rsi": 90.8
      },
      {
        "ticker": "CL",
        "name": "콜게이트 팜올리브",
        "price": 85.63,
        "change": 0.74,
        "tier": 4,
        "rank": 341,
        "rsi": 71.6
      },
      {
        "ticker": "PWR",
        "name": "콴타 서비시스",
        "price": 483.07,
        "change": 0.37,
        "tier": 4,
        "rank": 350,
        "rsi": 85.1
      },
      {
        "ticker": "ORLY",
        "name": "오릴리 오토모티브",
        "price": 100.04,
        "change": -1.31,
        "tier": 4,
        "rank": 351,
        "rsi": 76.7
      },
      {
        "ticker": "GPC",
        "name": "제뉴인 파츠",
        "price": 139.39,
        "change": -0.45,
        "tier": 4,
        "rank": 353,
        "rsi": 76.5
      },
      {
        "ticker": "DTE",
        "name": "DTE 에너지",
        "price": 136.98,
        "change": 0.3,
        "tier": 4,
        "rank": 359,
        "rsi": 78.1
      },
      {
        "ticker": "WMB",
        "name": "윌리엄스 컴퍼니스",
        "price": 67.15,
        "change": 0.34,
        "tier": 4,
        "rank": 362,
        "rsi": 76.2
      },
      {
        "ticker": "PEP",
        "name": "펩시코",
        "price": 149.62,
        "change": 0.75,
        "tier": 4,
        "rank": 370,
        "rsi": 78.7
      },
      {
        "ticker": "GLW",
        "name": "코닝",
        "price": 100.83,
        "change": -3.31,
        "tier": 4,
        "rank": 375,
        "rsi": 70.0
      },
      {
        "ticker": "TXN",
        "name": "텍사스 인스트루먼츠",
        "price": 219.81,
        "change": 1.68,
        "tier": 4,
        "rank": 389,
        "rsi": 80.8
      },
      {
        "ticker": "AZO",
        "name": "오토존",
        "price": 3741.64,
        "change": -1.07,
        "tier": 4,
        "rank": 391,
        "rsi": 82.4
      },
      {
        "ticker": "CME",
        "name": "CME 그룹",
        "price": 291.15,
        "change": 1.78,
        "tier": 4,
        "rank": 392,
        "rsi": 80.8
      },
      {
        "ticker": "ICE",
        "name": "인터컨티넨탈 익스체인지",
        "price": 174.92,
        "change": 1.44,
        "tier": 4,
        "rank": 393,
        "rsi": 73.8
      },
      {
        "ticker": "KEYS",
        "name": "키사이트 테크놀로지스",
        "price": 221.2,
        "change": -0.14,
        "tier": 4,
        "rank": 400,
        "rsi": 76.2
      },
      {
        "ticker": "CVX",
        "name": "셰브론",
        "price": 172.5,
        "change": 1.51,
        "tier": 5,
        "rank": 406,
        "rsi": 87.9
      },
      {
        "ticker": "TER",
        "name": "테라다인",
        "price": 247.42,
        "change": -1.22,
        "tier": 5,
        "rank": 410,
        "rsi": 77.8
      },
      {
        "ticker": "SLB",
        "name": "슐럼버거",
        "price": 49.21,
        "change": 0.7,
        "tier": 5,
        "rank": 417,
        "rsi": 73.5
      },
      {
        "ticker": "TPL",
        "name": "텍사스 퍼시픽 랜드",
        "price": 358.38,
        "change": 1.01,
        "tier": 5,
        "rank": 420,
        "rsi": 81.0
      },
      {
        "ticker": "BKR",
        "name": "베이커 휴즈",
        "price": 57.22,
        "change": 1.03,
        "tier": 5,
        "rank": 425,
        "rsi": 74.9
      },
      {
        "ticker": "LW",
        "name": "램 웨스턴 홀딩스",
        "price": 45.83,
        "change": 0.8,
        "tier": 5,
        "rank": 432,
        "rsi": 82.7
      },
      {
        "ticker": "TSN",
        "name": "타이슨 푸드",
        "price": 65.32,
        "change": 1.12,
        "tier": 5,
        "rank": 436,
        "rsi": 81.0
      },
      {
        "ticker": "CARR",
        "name": "캐리어 글로벌",
        "price": 59.16,
        "change": 2.16,
        "tier": 5,
        "rank": 442,
        "rsi": 74.3
      },
      {
        "ticker": "CHD",
        "name": "처치 앤드 드와이트",
        "price": 91.75,
        "change": 0.29,
        "tier": 5,
        "rank": 450,
        "rsi": 77.9
      },
      {
        "ticker": "GNRC",
        "name": "제네락 홀딩스",
        "price": 170.15,
        "change": -2.31,
        "tier": 5,
        "rank": 476,
        "rsi": 72.7
      },
      {
        "ticker": "MRNA",
        "name": "모더나",
        "price": 46.14,
        "change": 1.85,
        "tier": 5,
        "rank": 499,
        "rsi": 71.3
      }
    ],
    "rsi_oversold": [
      {
        "ticker": "SYF",
        "name": "싱크로니 파이낸셜",
        "price": 73.61,
        "change": 0.26,
        "tier": 1,
        "rank": 2,
        "rsi": 23.0
      },
      {
        "ticker": "LVS",
        "name": "라스베이거스 샌즈",
        "price": 52.72,
        "change": -13.94,
        "tier": 1,
        "rank": 4,
        "rsi": 25.9
      },
      {
        "ticker": "PTC",
        "name": "PTC",
        "price": 153.07,
        "change": -5.46,
        "tier": 1,
        "rank": 15,
        "rsi": 21.3
      },
      {
        "ticker": "UBER",
        "name": "우버 테크놀로지스",
        "price": 81.39,
        "change": 2.02,
        "tier": 2,
        "rank": 26,
        "rsi": 26.0
      },
      {
        "ticker": "SOLV",
        "name": "솔벤텀",
        "price": 76.12,
        "change": -0.62,
        "tier": 2,
        "rank": 28,
        "rsi": 16.1
      },
      {
        "ticker": "PLTR",
        "name": "팔란티어 테크놀로지스",
        "price": 149.96,
        "change": -4.7,
        "tier": 2,
        "rank": 30,
        "rsi": 16.8
      },
      {
        "ticker": "ADBE",
        "name": "어도비",
        "price": 288.08,
        "change": -3.84,
        "tier": 2,
        "rank": 34,
        "rsi": 19.7
      },
      {
        "ticker": "BR",
        "name": "브로드리지 파이낸셜 솔루션스",
        "price": 197.42,
        "change": -3.65,
        "tier": 2,
        "rank": 39,
        "rsi": 13.5
      },
      {
        "ticker": "BAC",
        "name": "뱅크 오브 아메리카",
        "price": 52.81,
        "change": 1.94,
        "tier": 2,
        "rank": 43,
        "rsi": 29.0
      },
      {
        "ticker": "HOOD",
        "name": "로빈후드 마켓",
        "price": 100.92,
        "change": -2.4,
        "tier": 2,
        "rank": 45,
        "rsi": 23.1
      },
      {
        "ticker": "REGN",
        "name": "리제네론 파마슈티컬스",
        "price": 744.83,
        "change": -0.84,
        "tier": 2,
        "rank": 70,
        "rsi": 29.4
      },
      {
        "ticker": "GEN",
        "name": "젠 디지털",
        "price": 23.84,
        "change": -3.83,
        "tier": 2,
        "rank": 71,
        "rsi": 21.9
      },
      {
        "ticker": "PAYC",
        "name": "페이콤 소프트웨어",
        "price": 133.46,
        "change": -4.43,
        "tier": 2,
        "rank": 75,
        "rsi": 18.0
      },
      {
        "ticker": "ISRG",
        "name": "인튜이티브 서지컬",
        "price": 504.24,
        "change": -3.41,
        "tier": 2,
        "rank": 79,
        "rsi": 8.3
      },
      {
        "ticker": "TJX",
        "name": "TJX 컴퍼니즈",
        "price": 146.56,
        "change": -0.83,
        "tier": 2,
        "rank": 86,
        "rsi": 18.0
      },
      {
        "ticker": "FOXA",
        "name": "폭스 A",
        "price": 71.79,
        "change": 0.91,
        "tier": 2,
        "rank": 95,
        "rsi": 26.6
      },
      {
        "ticker": "TRMB",
        "name": "트림블",
        "price": 68.1,
        "change": -2.81,
        "tier": 3,
        "rank": 104,
        "rsi": 18.8
      },
      {
        "ticker": "A",
        "name": "애질런트 테크놀로지스",
        "price": 132.91,
        "change": -0.71,
        "tier": 3,
        "rank": 105,
        "rsi": 27.1
      },
      {
        "ticker": "URI",
        "name": "유나이티드 렌탈스",
        "price": 767.03,
        "change": -15.08,
        "tier": 3,
        "rank": 109,
        "rsi": 26.5
      },
      {
        "ticker": "FOX",
        "name": "폭스 B",
        "price": 64.84,
        "change": 0.86,
        "tier": 3,
        "rank": 114,
        "rsi": 27.9
      },
      {
        "ticker": "MA",
        "name": "마스터카드",
        "price": 537.79,
        "change": 3.15,
        "tier": 3,
        "rank": 115,
        "rsi": 28.1
      },
      {
        "ticker": "CRM",
        "name": "세일즈포스",
        "price": 212.48,
        "change": -6.79,
        "tier": 3,
        "rank": 117,
        "rsi": 14.0
      },
      {
        "ticker": "GDDY",
        "name": "고대디",
        "price": 99.71,
        "change": -3.53,
        "tier": 3,
        "rank": 136,
        "rsi": 18.9
      },
      {
        "ticker": "INTU",
        "name": "인튜이트",
        "price": 496.2,
        "change": -7.89,
        "tier": 3,
        "rank": 139,
        "rsi": 16.6
      },
      {
        "ticker": "APO",
        "name": "아폴로 글로벌 매니지먼트",
        "price": 134.34,
        "change": 1.09,
        "tier": 3,
        "rank": 149,
        "rsi": 22.3
      },
      {
        "ticker": "NFLX",
        "name": "넷플릭스",
        "price": 82.61,
        "change": -2.4,
        "tier": 3,
        "rank": 150,
        "rsi": 23.4
      },
      {
        "ticker": "LULU",
        "name": "룰루레몬 애슬레티카",
        "price": 174.87,
        "change": -3.04,
        "tier": 3,
        "rank": 151,
        "rsi": 24.2
      },
      {
        "ticker": "COIN",
        "name": "코인베이스",
        "price": 196.55,
        "change": -6.15,
        "tier": 3,
        "rank": 153,
        "rsi": 20.4
      },
      {
        "ticker": "WYNN",
        "name": "윈 리조트",
        "price": 108.99,
        "change": -3.45,
        "tier": 3,
        "rank": 164,
        "rsi": 26.6
      },
      {
        "ticker": "GEHC",
        "name": "GE 헬스케어",
        "price": 78.04,
        "change": -1.54,
        "tier": 3,
        "rank": 195,
        "rsi": 22.5
      },
      {
        "ticker": "PYPL",
        "name": "페이팔 홀딩스",
        "price": 53.17,
        "change": -1.67,
        "tier": 3,
        "rank": 196,
        "rsi": 28.3
      },
      {
        "ticker": "ROP",
        "name": "로퍼 테크놀로지스",
        "price": 358.39,
        "change": -0.55,
        "tier": 3,
        "rank": 203,
        "rsi": 7.9
      },
      {
        "ticker": "PAYX",
        "name": "페이첵스",
        "price": 102.94,
        "change": 0.48,
        "tier": 3,
        "rank": 219,
        "rsi": 13.1
      },
      {
        "ticker": "V",
        "name": "비자",
        "price": 330.85,
        "change": 1.18,
        "tier": 3,
        "rank": 220,
        "rsi": 25.2
      },
      {
        "ticker": "JPM",
        "name": "제이피모건 체이스",
        "price": 305.19,
        "change": 1.47,
        "tier": 3,
        "rank": 236,
        "rsi": 27.0
      },
      {
        "ticker": "COF",
        "name": "캐피털 원 파이낸셜",
        "price": 219.09,
        "change": 0.31,
        "tier": 3,
        "rank": 237,
        "rsi": 25.4
      },
      {
        "ticker": "BRK.B",
        "name": "버크셔 해서웨이 B",
        "price": 475.85,
        "change": 0.5,
        "tier": 3,
        "rank": 238,
        "rsi": 20.3
      },
      {
        "ticker": "ADP",
        "name": "오토매틱 데이터 프로세싱",
        "price": 247.56,
        "change": -1.25,
        "tier": 3,
        "rank": 246,
        "rsi": 24.6
      },
      {
        "ticker": "QCOM",
        "name": "퀄컴",
        "price": 151.73,
        "change": -0.64,
        "tier": 4,
        "rank": 255,
        "rsi": 9.9
      },
      {
        "ticker": "PODD",
        "name": "인슐릿",
        "price": 255.51,
        "change": -1.04,
        "tier": 4,
        "rank": 284,
        "rsi": 17.7
      },
      {
        "ticker": "HUM",
        "name": "휴매나",
        "price": 194.65,
        "change": 0.33,
        "tier": 4,
        "rank": 299,
        "rsi": 12.3
      },
      {
        "ticker": "FIS",
        "name": "피델리티 내셔널 인포메이션 서비시스",
        "price": 55.55,
        "change": -1.14,
        "tier": 4,
        "rank": 303,
        "rsi": 8.5
      },
      {
        "ticker": "DASH",
        "name": "도어대시",
        "price": 208.9,
        "change": 1.08,
        "tier": 4,
        "rank": 304,
        "rsi": 27.5
      },
      {
        "ticker": "ABT",
        "name": "애보트",
        "price": 106.09,
        "change": 0.04,
        "tier": 4,
        "rank": 309,
        "rsi": 8.6
      },
      {
        "ticker": "PRU",
        "name": "푸르덴셜 파이낸셜",
        "price": 109.36,
        "change": 1.56,
        "tier": 4,
        "rank": 312,
        "rsi": 27.0
      },
      {
        "ticker": "WST",
        "name": "웨스트 파마슈티컬 서비시스",
        "price": 229.32,
        "change": -2.79,
        "tier": 4,
        "rank": 319,
        "rsi": 21.5
      },
      {
        "ticker": "ARES",
        "name": "아레스 매니지먼트",
        "price": 150.52,
        "change": 0.48,
        "tier": 4,
        "rank": 321,
        "rsi": 7.2
      },
      {
        "ticker": "TTD",
        "name": "트레이드 데스크",
        "price": 31.43,
        "change": -1.36,
        "tier": 4,
        "rank": 329,
        "rsi": 24.9
      },
      {
        "ticker": "WDAY",
        "name": "워크데이",
        "price": 172.73,
        "change": -8.67,
        "tier": 4,
        "rank": 343,
        "rsi": 16.5
      },
      {
        "ticker": "WTW",
        "name": "윌리스 타워스 왓슨",
        "price": 318.31,
        "change": 1.27,
        "tier": 4,
        "rank": 347,
        "rsi": 28.4
      },
      {
        "ticker": "TYL",
        "name": "타일러 테크놀로지스",
        "price": 390.48,
        "change": -6.83,
        "tier": 4,
        "rank": 349,
        "rsi": 22.6
      },
      {
        "ticker": "ZBH",
        "name": "짐머 바이오멧 홀딩스",
        "price": 85.14,
        "change": -0.67,
        "tier": 4,
        "rank": 354,
        "rsi": 18.4
      },
      {
        "ticker": "NOW",
        "name": "서비스나우",
        "price": 114.76,
        "change": -11.46,
        "tier": 4,
        "rank": 360,
        "rsi": 21.5
      },
      {
        "ticker": "PANW",
        "name": "팔로알토 네트웍스",
        "price": 172.62,
        "change": -6.05,
        "tier": 4,
        "rank": 365,
        "rsi": 22.0
      },
      {
        "ticker": "HPQ",
        "name": "HP",
        "price": 19.56,
        "change": 2.68,
        "tier": 4,
        "rank": 387,
        "rsi": 25.1
      },
      {
        "ticker": "FDS",
        "name": "팩트셋 리서치 시스템즈",
        "price": 255.23,
        "change": -5.42,
        "tier": 4,
        "rank": 396,
        "rsi": 24.8
      },
      {
        "ticker": "KKR",
        "name": "KKR & CO",
        "price": 115.05,
        "change": -1.47,
        "tier": 5,
        "rank": 402,
        "rsi": 18.2
      },
      {
        "ticker": "TTWO",
        "name": "테이크 투 인터랙티브 소프트웨어",
        "price": 237.91,
        "change": -2.17,
        "tier": 5,
        "rank": 419,
        "rsi": 26.2
      },
      {
        "ticker": "PSKY",
        "name": "파라마운트 스카이댄스 코퍼레이션",
        "price": 11.02,
        "change": -2.78,
        "tier": 5,
        "rank": 426,
        "rsi": 22.5
      },
      {
        "ticker": "BBY",
        "name": "베스트 바이",
        "price": 65.78,
        "change": 0.34,
        "tier": 5,
        "rank": 430,
        "rsi": 25.8
      },
      {
        "ticker": "BRO",
        "name": "브라운 앤 브라운",
        "price": 72.28,
        "change": 0.24,
        "tier": 5,
        "rank": 435,
        "rsi": 19.8
      },
      {
        "ticker": "AJG",
        "name": "아서 J 갤러거",
        "price": 244.71,
        "change": 0.97,
        "tier": 5,
        "rank": 466,
        "rsi": 25.6
      },
      {
        "ticker": "AXON",
        "name": "액손 엔터프라이즈",
        "price": 514.84,
        "change": -6.37,
        "tier": 5,
        "rank": 482,
        "rsi": 24.6
      },
      {
        "ticker": "FISV",
        "name": "파이서브",
        "price": 63.86,
        "change": -1.68,
        "tier": 5,
        "rank": 501,
        "rsi": 29.8
      }
    ],
    "candle_bullish": [
      {
        "ticker": "INCY",
        "name": "인사이트",
        "price": 101.41,
        "change": 0.23,
        "tier": 1,
        "rank": 13,
        "pattern": "망치형",
        "desc": "하락 추세에서 바닥 반전 신호"
      },
      {
        "ticker": "VZ",
        "name": "버라이즌 커뮤니케이션스",
        "price": 39.96,
        "change": 1.38,
        "tier": 1,
        "rank": 21,
        "pattern": "샛별형",
        "desc": "강력한 바닥 반전 3봉 패턴"
      },
      {
        "ticker": "BK",
        "name": "뉴욕멜론은행",
        "price": 119.78,
        "change": 0.74,
        "tier": 2,
        "rank": 64,
        "pattern": "샛별형",
        "desc": "강력한 바닥 반전 3봉 패턴"
      },
      {
        "ticker": "VTR",
        "name": "벤타스",
        "price": 76.93,
        "change": 1.32,
        "tier": 2,
        "rank": 89,
        "pattern": "샛별형",
        "desc": "강력한 바닥 반전 3봉 패턴"
      },
      {
        "ticker": "CMCSA",
        "name": "컴캐스트",
        "price": 29.46,
        "change": 3.7,
        "tier": 3,
        "rank": 108,
        "pattern": "상승 장악형",
        "desc": "강력한 매수세로 추세 반전"
      },
      {
        "ticker": "MA",
        "name": "마스터카드",
        "price": 537.79,
        "change": 3.15,
        "tier": 3,
        "rank": 115,
        "pattern": "샛별형",
        "desc": "강력한 바닥 반전 3봉 패턴"
      },
      {
        "ticker": "RCL",
        "name": "로얄 캐리비안 크루즈",
        "price": 335.17,
        "change": 14.94,
        "tier": 3,
        "rank": 180,
        "pattern": "샛별형",
        "desc": "강력한 바닥 반전 3봉 패턴"
      },
      {
        "ticker": "TKO",
        "name": "TKO 그룹 홀딩스",
        "price": 195.77,
        "change": 0.46,
        "tier": 3,
        "rank": 184,
        "pattern": "망치형",
        "desc": "하락 추세에서 바닥 반전 신호"
      },
      {
        "ticker": "CBRE",
        "name": "CBRE 그룹",
        "price": 170.84,
        "change": 0.79,
        "tier": 3,
        "rank": 185,
        "pattern": "샛별형",
        "desc": "강력한 바닥 반전 3봉 패턴"
      },
      {
        "ticker": "DGX",
        "name": "퀘스트 다이아그노스틱스",
        "price": 183.49,
        "change": 0.41,
        "tier": 3,
        "rank": 194,
        "pattern": "상승 장악형",
        "desc": "강력한 매수세로 추세 반전"
      },
      {
        "ticker": "NSC",
        "name": "노퍽 서던",
        "price": 288.76,
        "change": 1.51,
        "tier": 3,
        "rank": 215,
        "pattern": "상승 장악형",
        "desc": "강력한 매수세로 추세 반전"
      },
      {
        "ticker": "PAYX",
        "name": "페이첵스",
        "price": 102.94,
        "change": 0.48,
        "tier": 3,
        "rank": 219,
        "pattern": "상승 장악형",
        "desc": "강력한 매수세로 추세 반전"
      },
      {
        "ticker": "V",
        "name": "비자",
        "price": 330.85,
        "change": 1.18,
        "tier": 3,
        "rank": 220,
        "pattern": "샛별형",
        "desc": "강력한 바닥 반전 3봉 패턴"
      },
      {
        "ticker": "PG",
        "name": "P&G",
        "price": 150.0,
        "change": 1.81,
        "tier": 3,
        "rank": 222,
        "pattern": "상승 장악형",
        "desc": "강력한 매수세로 추세 반전"
      },
      {
        "ticker": "CHTR",
        "name": "차터 커뮤니케이션스",
        "price": 188.24,
        "change": 2.97,
        "tier": 4,
        "rank": 264,
        "pattern": "상승 장악형",
        "desc": "강력한 매수세로 추세 반전"
      },
      {
        "ticker": "KMB",
        "name": "킴벌리 클라크",
        "price": 99.56,
        "change": 0.02,
        "tier": 4,
        "rank": 326,
        "pattern": "망치형",
        "desc": "하락 추세에서 바닥 반전 신호"
      },
      {
        "ticker": "WTW",
        "name": "윌리스 타워스 왓슨",
        "price": 318.31,
        "change": 1.27,
        "tier": 4,
        "rank": 347,
        "pattern": "샛별형",
        "desc": "강력한 바닥 반전 3봉 패턴"
      },
      {
        "ticker": "MRSH",
        "name": "마시 앤드 맥레넌",
        "price": 185.65,
        "change": 4.19,
        "tier": 4,
        "rank": 357,
        "pattern": "샛별형",
        "desc": "강력한 바닥 반전 3봉 패턴"
      },
      {
        "ticker": "ITW",
        "name": "일리노이 툴 웍스",
        "price": 260.77,
        "change": 0.98,
        "tier": 4,
        "rank": 379,
        "pattern": "샛별형",
        "desc": "강력한 바닥 반전 3봉 패턴"
      },
      {
        "ticker": "ICE",
        "name": "인터컨티넨탈 익스체인지",
        "price": 174.92,
        "change": 1.44,
        "tier": 4,
        "rank": 393,
        "pattern": "샛별형",
        "desc": "강력한 바닥 반전 3봉 패턴"
      },
      {
        "ticker": "CNC",
        "name": "센틴",
        "price": 43.33,
        "change": 3.42,
        "tier": 5,
        "rank": 455,
        "pattern": "샛별형",
        "desc": "강력한 바닥 반전 3봉 패턴"
      },
      {
        "ticker": "ERIE",
        "name": "이리 인뎀너티",
        "price": 282.86,
        "change": 3.41,
        "tier": 5,
        "rank": 480,
        "pattern": "샛별형",
        "desc": "강력한 바닥 반전 3봉 패턴"
      }
    ],
    "candle_bearish": [
      {
        "ticker": "NEM",
        "name": "뉴몬트",
        "price": 125.08,
        "change": -5.21,
        "tier": 1,
        "rank": 3,
        "pattern": "하락 장악형",
        "desc": "강력한 매도세로 추세 반전"
      },
      {
        "ticker": "UHS",
        "name": "유니버설 헬스 서비시스",
        "price": 200.95,
        "change": -1.02,
        "tier": 1,
        "rank": 5,
        "pattern": "하락 장악형",
        "desc": "강력한 매도세로 추세 반전"
      },
      {
        "ticker": "GL",
        "name": "글로브 라이프",
        "price": 138.95,
        "change": 0.29,
        "tier": 1,
        "rank": 20,
        "pattern": "유성형",
        "desc": "상승 추세에서 고점 반전 신호"
      },
      {
        "ticker": "MSFT",
        "name": "마이크로소프트",
        "price": 424.29,
        "change": -11.91,
        "tier": 2,
        "rank": 51,
        "pattern": "석별형",
        "desc": "강력한 고점 반전 3봉 패턴"
      },
      {
        "ticker": "JKHY",
        "name": "잭 헨리 앤드 어소시에이츠",
        "price": 179.01,
        "change": -0.44,
        "tier": 2,
        "rank": 67,
        "pattern": "하락 장악형",
        "desc": "강력한 매도세로 추세 반전"
      },
      {
        "ticker": "ELV",
        "name": "엘리번스 헬스",
        "price": 344.26,
        "change": 0.7,
        "tier": 2,
        "rank": 76,
        "pattern": "유성형",
        "desc": "상승 추세에서 고점 반전 신호"
      },
      {
        "ticker": "GILD",
        "name": "길리어드 사이언스",
        "price": 139.13,
        "change": -0.42,
        "tier": 2,
        "rank": 83,
        "pattern": "석별형",
        "desc": "강력한 고점 반전 3봉 패턴"
      },
      {
        "ticker": "JBL",
        "name": "자빌",
        "price": 240.63,
        "change": -1.23,
        "tier": 2,
        "rank": 99,
        "pattern": "하락 장악형",
        "desc": "강력한 매도세로 추세 반전"
      },
      {
        "ticker": "CSCO",
        "name": "시스코 시스템즈",
        "price": 78.09,
        "change": -1.1,
        "tier": 3,
        "rank": 119,
        "pattern": "하락 장악형",
        "desc": "강력한 매도세로 추세 반전"
      },
      {
        "ticker": "DD",
        "name": "듀폰 드 느무르",
        "price": 44.25,
        "change": -0.85,
        "tier": 3,
        "rank": 204,
        "pattern": "석별형",
        "desc": "강력한 고점 반전 3봉 패턴"
      },
      {
        "ticker": "MS",
        "name": "모간 스탠리",
        "price": 180.62,
        "change": -0.94,
        "tier": 3,
        "rank": 206,
        "pattern": "석별형",
        "desc": "강력한 고점 반전 3봉 패턴"
      },
      {
        "ticker": "IQV",
        "name": "아이큐비아 홀딩스",
        "price": 236.75,
        "change": -1.26,
        "tier": 3,
        "rank": 216,
        "pattern": "하락 장악형",
        "desc": "강력한 매도세로 추세 반전"
      },
      {
        "ticker": "GS",
        "name": "골드만삭스 그룹",
        "price": 931.82,
        "change": -0.53,
        "tier": 3,
        "rank": 250,
        "pattern": "하락 장악형",
        "desc": "강력한 매도세로 추세 반전"
      },
      {
        "ticker": "QCOM",
        "name": "퀄컴",
        "price": 151.73,
        "change": -0.64,
        "tier": 4,
        "rank": 255,
        "pattern": "하락 장악형",
        "desc": "강력한 매도세로 추세 반전"
      },
      {
        "ticker": "AES",
        "name": "AES",
        "price": 14.9,
        "change": -1.88,
        "tier": 4,
        "rank": 346,
        "pattern": "하락 장악형",
        "desc": "강력한 매도세로 추세 반전"
      },
      {
        "ticker": "ORLY",
        "name": "오릴리 오토모티브",
        "price": 100.04,
        "change": -1.31,
        "tier": 4,
        "rank": 351,
        "pattern": "하락 장악형",
        "desc": "강력한 매도세로 추세 반전"
      },
      {
        "ticker": "GPC",
        "name": "제뉴인 파츠",
        "price": 139.39,
        "change": -0.45,
        "tier": 4,
        "rank": 353,
        "pattern": "하락 장악형",
        "desc": "강력한 매도세로 추세 반전"
      },
      {
        "ticker": "VST",
        "name": "비스트라 에너지",
        "price": 161.03,
        "change": -2.78,
        "tier": 5,
        "rank": 472,
        "pattern": "석별형",
        "desc": "강력한 고점 반전 3봉 패턴"
      },
      {
        "ticker": "GNRC",
        "name": "제네락 홀딩스",
        "price": 170.15,
        "change": -2.31,
        "tier": 5,
        "rank": 476,
        "pattern": "하락 장악형",
        "desc": "강력한 매도세로 추세 반전"
      },
      {
        "ticker": "J",
        "name": "제이콥스 솔루션즈",
        "price": 135.42,
        "change": -0.94,
        "tier": 5,
        "rank": 484,
        "pattern": "하락 장악형",
        "desc": "강력한 매도세로 추세 반전"
      },
      {
        "ticker": "LEN",
        "name": "레나",
        "price": 111.54,
        "change": 0.68,
        "tier": 5,
        "rank": 488,
        "pattern": "유성형",
        "desc": "상승 추세에서 고점 반전 신호"
      },
      {
        "ticker": "BAX",
        "name": "박스터 인터내셔널",
        "price": 19.44,
        "change": -0.87,
        "tier": 5,
        "rank": 495,
        "pattern": "하락 장악형",
        "desc": "강력한 매도세로 추세 반전"
      }
    ],
    "volume_spike": [
      {
        "ticker": "FSLR",
        "name": "퍼스트 솔라",
        "price": 221.3,
        "change": -11.27,
        "tier": 1,
        "rank": 1,
        "score": 4.8
      },
      {
        "ticker": "NEM",
        "name": "뉴몬트",
        "price": 125.08,
        "change": -5.21,
        "tier": 1,
        "rank": 3,
        "score": 4.6
      },
      {
        "ticker": "LVS",
        "name": "라스베이거스 샌즈",
        "price": 52.72,
        "change": -13.94,
        "tier": 1,
        "rank": 4,
        "score": 5.0
      },
      {
        "ticker": "MU",
        "name": "마이크론 테크놀로지",
        "price": 430.0,
        "change": -1.21,
        "tier": 1,
        "rank": 12,
        "score": 4.5
      },
      {
        "ticker": "PTC",
        "name": "PTC",
        "price": 153.07,
        "change": -5.46,
        "tier": 1,
        "rank": 15,
        "score": 4.3
      },
      {
        "ticker": "CCL",
        "name": "카니발",
        "price": 30.84,
        "change": 7.38,
        "tier": 1,
        "rank": 19,
        "score": 4.8
      },
      {
        "ticker": "UBER",
        "name": "우버 테크놀로지스",
        "price": 81.39,
        "change": 2.02,
        "tier": 2,
        "rank": 26,
        "score": 4.3
      },
      {
        "ticker": "PLTR",
        "name": "팔란티어 테크놀로지스",
        "price": 149.96,
        "change": -4.7,
        "tier": 2,
        "rank": 30,
        "score": 4.5
      },
      {
        "ticker": "TXT",
        "name": "텍스트론",
        "price": 88.17,
        "change": 1.58,
        "tier": 2,
        "rank": 31,
        "score": 4.4
      },
      {
        "ticker": "ADBE",
        "name": "어도비",
        "price": 288.08,
        "change": -3.84,
        "tier": 2,
        "rank": 34,
        "score": 4.6
      },
      {
        "ticker": "BR",
        "name": "브로드리지 파이낸셜 솔루션스",
        "price": 197.42,
        "change": -3.65,
        "tier": 2,
        "rank": 39,
        "score": 4.1
      },
      {
        "ticker": "APH",
        "name": "암페놀",
        "price": 149.31,
        "change": 2.3,
        "tier": 2,
        "rank": 40,
        "score": 4.7
      },
      {
        "ticker": "DVN",
        "name": "데번 에너지",
        "price": 40.44,
        "change": 1.53,
        "tier": 2,
        "rank": 41,
        "score": 4.0
      },
      {
        "ticker": "CVNA",
        "name": "카바나",
        "price": 417.38,
        "change": 1.79,
        "tier": 2,
        "rank": 42,
        "score": 4.7
      },
      {
        "ticker": "HOOD",
        "name": "로빈후드 마켓",
        "price": 100.92,
        "change": -2.4,
        "tier": 2,
        "rank": 45,
        "score": 4.0
      },
      {
        "ticker": "MSFT",
        "name": "마이크로소프트",
        "price": 424.29,
        "change": -11.91,
        "tier": 2,
        "rank": 51,
        "score": 5.0
      },
      {
        "ticker": "AOS",
        "name": "A O 스미스",
        "price": 73.96,
        "change": 6.44,
        "tier": 2,
        "rank": 61,
        "score": 4.8
      },
      {
        "ticker": "PNR",
        "name": "펜테어",
        "price": 105.06,
        "change": -0.1,
        "tier": 2,
        "rank": 65,
        "score": 4.1
      },
      {
        "ticker": "GEN",
        "name": "젠 디지털",
        "price": 23.84,
        "change": -3.83,
        "tier": 2,
        "rank": 71,
        "score": 4.9
      },
      {
        "ticker": "PAYC",
        "name": "페이콤 소프트웨어",
        "price": 133.46,
        "change": -4.43,
        "tier": 2,
        "rank": 75,
        "score": 4.7
      },
      {
        "ticker": "ORCL",
        "name": "오라클",
        "price": 164.35,
        "change": -4.89,
        "tier": 2,
        "rank": 78,
        "score": 4.5
      },
      {
        "ticker": "PH",
        "name": "파커 하니핀",
        "price": 958.5,
        "change": 4.61,
        "tier": 2,
        "rank": 91,
        "score": 4.5
      },
      {
        "ticker": "EOG",
        "name": "EOG 리소시스",
        "price": 113.61,
        "change": 2.33,
        "tier": 2,
        "rank": 94,
        "score": 4.1
      },
      {
        "ticker": "TRMB",
        "name": "트림블",
        "price": 68.1,
        "change": -2.81,
        "tier": 3,
        "rank": 104,
        "score": 4.7
      },
      {
        "ticker": "CMCSA",
        "name": "컴캐스트",
        "price": 29.46,
        "change": 3.7,
        "tier": 3,
        "rank": 108,
        "score": 4.5
      },
      {
        "ticker": "URI",
        "name": "유나이티드 렌탈스",
        "price": 767.03,
        "change": -15.08,
        "tier": 3,
        "rank": 109,
        "score": 5.0
      },
      {
        "ticker": "MA",
        "name": "마스터카드",
        "price": 537.79,
        "change": 3.15,
        "tier": 3,
        "rank": 115,
        "score": 4.4
      },
      {
        "ticker": "CRM",
        "name": "세일즈포스",
        "price": 212.48,
        "change": -6.79,
        "tier": 3,
        "rank": 117,
        "score": 4.8
      },
      {
        "ticker": "ANET",
        "name": "아리스타 네트웍스",
        "price": 148.19,
        "change": -1.31,
        "tier": 3,
        "rank": 120,
        "score": 4.0
      },
      {
        "ticker": "ADSK",
        "name": "오토데스크",
        "price": 254.54,
        "change": -5.14,
        "tier": 3,
        "rank": 125,
        "score": 4.8
      },
      {
        "ticker": "DOV",
        "name": "도버",
        "price": 204.66,
        "change": -0.65,
        "tier": 3,
        "rank": 130,
        "score": 4.7
      },
      {
        "ticker": "HON",
        "name": "허니웰 인터내셔널",
        "price": 225.58,
        "change": 4.13,
        "tier": 3,
        "rank": 131,
        "score": 4.1
      },
      {
        "ticker": "CHRW",
        "name": "CH 로빈슨 월드와이드",
        "price": 191.2,
        "change": 3.76,
        "tier": 3,
        "rank": 138,
        "score": 4.8
      },
      {
        "ticker": "INTU",
        "name": "인튜이트",
        "price": 496.2,
        "change": -7.89,
        "tier": 3,
        "rank": 139,
        "score": 4.9
      },
      {
        "ticker": "STX",
        "name": "씨게이트 테크놀로지",
        "price": 438.36,
        "change": -1.03,
        "tier": 3,
        "rank": 140,
        "score": 4.7
      },
      {
        "ticker": "FCX",
        "name": "프리포트 맥모란",
        "price": 64.85,
        "change": 1.91,
        "tier": 3,
        "rank": 142,
        "score": 4.9
      },
      {
        "ticker": "TT",
        "name": "트레인 테크놀로지스",
        "price": 426.78,
        "change": 8.26,
        "tier": 3,
        "rank": 144,
        "score": 4.9
      },
      {
        "ticker": "WEC",
        "name": "WEC 에너지 그룹",
        "price": 110.46,
        "change": 0.38,
        "tier": 3,
        "rank": 148,
        "score": 4.1
      },
      {
        "ticker": "COIN",
        "name": "코인베이스",
        "price": 196.55,
        "change": -6.15,
        "tier": 3,
        "rank": 153,
        "score": 4.6
      },
      {
        "ticker": "RTX",
        "name": "RTX",
        "price": 199.69,
        "change": 0.11,
        "tier": 3,
        "rank": 157,
        "score": 4.3
      },
      {
        "ticker": "AVB",
        "name": "아발론베이 커뮤니티스",
        "price": 175.08,
        "change": 1.22,
        "tier": 3,
        "rank": 161,
        "score": 4.4
      },
      {
        "ticker": "COP",
        "name": "코노코필립스",
        "price": 104.63,
        "change": 3.2,
        "tier": 3,
        "rank": 162,
        "score": 4.2
      },
      {
        "ticker": "WYNN",
        "name": "윈 리조트",
        "price": 108.99,
        "change": -3.45,
        "tier": 3,
        "rank": 164,
        "score": 4.1
      },
      {
        "ticker": "LHX",
        "name": "L3해리스 테크놀로지스",
        "price": 353.93,
        "change": -1.77,
        "tier": 3,
        "rank": 167,
        "score": 4.2
      },
      {
        "ticker": "PHM",
        "name": "폴티 그룹",
        "price": 127.48,
        "change": 3.42,
        "tier": 3,
        "rank": 171,
        "score": 4.0
      },
      {
        "ticker": "FICO",
        "name": "페어 아이작",
        "price": 1563.0,
        "change": 2.45,
        "tier": 3,
        "rank": 175,
        "score": 4.6
      },
      {
        "ticker": "T",
        "name": "AT&T",
        "price": 24.82,
        "change": 3.1,
        "tier": 3,
        "rank": 177,
        "score": 4.2
      },
      {
        "ticker": "KIM",
        "name": "킴코 리얼티",
        "price": 20.67,
        "change": 0.9,
        "tier": 3,
        "rank": 178,
        "score": 4.9
      },
      {
        "ticker": "RCL",
        "name": "로얄 캐리비안 크루즈",
        "price": 335.17,
        "change": 14.94,
        "tier": 3,
        "rank": 180,
        "score": 4.9
      },
      {
        "ticker": "AON",
        "name": "에이온",
        "price": 341.78,
        "change": 2.64,
        "tier": 3,
        "rank": 189,
        "score": 4.2
      },
      {
        "ticker": "MO",
        "name": "알트리아 그룹",
        "price": 61.47,
        "change": -2.64,
        "tier": 3,
        "rank": 191,
        "score": 4.6
      },
      {
        "ticker": "AMP",
        "name": "아메리프라이즈 파이낸셜",
        "price": 523.94,
        "change": 4.86,
        "tier": 3,
        "rank": 199,
        "score": 4.3
      },
      {
        "ticker": "LNT",
        "name": "얼라이언트 에너지",
        "price": 66.33,
        "change": 0.11,
        "tier": 3,
        "rank": 202,
        "score": 4.7
      },
      {
        "ticker": "ROP",
        "name": "로퍼 테크놀로지스",
        "price": 358.39,
        "change": -0.55,
        "tier": 3,
        "rank": 203,
        "score": 4.3
      },
      {
        "ticker": "WM",
        "name": "웨이스트 매니지먼트",
        "price": 226.49,
        "change": -2.21,
        "tier": 3,
        "rank": 208,
        "score": 4.5
      },
      {
        "ticker": "ACN",
        "name": "액센츄어",
        "price": 262.11,
        "change": -3.07,
        "tier": 3,
        "rank": 221,
        "score": 4.6
      },
      {
        "ticker": "CAT",
        "name": "캐터필러",
        "price": 669.58,
        "change": 4.09,
        "tier": 3,
        "rank": 226,
        "score": 4.4
      },
      {
        "ticker": "META",
        "name": "메타 플랫폼스(페이스북)",
        "price": 728.62,
        "change": 8.96,
        "tier": 3,
        "rank": 231,
        "score": 5.0
      },
      {
        "ticker": "XOM",
        "name": "엑슨 모빌",
        "price": 139.65,
        "change": 1.5,
        "tier": 3,
        "rank": 235,
        "score": 4.3
      },
      {
        "ticker": "NCLH",
        "name": "노르웨이지안 크루즈 라인 홀딩스",
        "price": 22.75,
        "change": 9.43,
        "tier": 3,
        "rank": 240,
        "score": 4.5
      },
      {
        "ticker": "APA",
        "name": "APA",
        "price": 26.9,
        "change": 3.42,
        "tier": 3,
        "rank": 243,
        "score": 4.1
      },
      {
        "ticker": "UNH",
        "name": "유나이티드헬스 그룹",
        "price": 292.66,
        "change": -0.46,
        "tier": 3,
        "rank": 248,
        "score": 4.5
      },
      {
        "ticker": "NTRS",
        "name": "노던 트러스트",
        "price": 150.34,
        "change": 0.06,
        "tier": 4,
        "rank": 260,
        "score": 4.1
      },
      {
        "ticker": "DHR",
        "name": "다나허",
        "price": 221.79,
        "change": -1.22,
        "tier": 4,
        "rank": 262,
        "score": 4.5
      },
      {
        "ticker": "CHTR",
        "name": "차터 커뮤니케이션스",
        "price": 188.24,
        "change": 2.97,
        "tier": 4,
        "rank": 264,
        "score": 4.0
      },
      {
        "ticker": "TSCO",
        "name": "트랙터 서플라이",
        "price": 51.61,
        "change": -6.4,
        "tier": 4,
        "rank": 265,
        "score": 4.9
      },
      {
        "ticker": "CDNS",
        "name": "케이던스 디자인 시스템즈",
        "price": 298.95,
        "change": -6.72,
        "tier": 4,
        "rank": 276,
        "score": 4.5
      },
      {
        "ticker": "PODD",
        "name": "인슐릿",
        "price": 255.51,
        "change": -1.04,
        "tier": 4,
        "rank": 284,
        "score": 4.0
      },
      {
        "ticker": "TMO",
        "name": "써모 피셔 사이언티픽",
        "price": 595.35,
        "change": -2.08,
        "tier": 4,
        "rank": 288,
        "score": 4.8
      },
      {
        "ticker": "OTIS",
        "name": "오티스 월드와이드",
        "price": 87.17,
        "change": -1.61,
        "tier": 4,
        "rank": 293,
        "score": 4.2
      },
      {
        "ticker": "HUM",
        "name": "휴매나",
        "price": 194.65,
        "change": 0.33,
        "tier": 4,
        "rank": 299,
        "score": 4.4
      },
      {
        "ticker": "FIS",
        "name": "피델리티 내셔널 인포메이션 서비시스",
        "price": 55.55,
        "change": -1.14,
        "tier": 4,
        "rank": 303,
        "score": 4.6
      },
      {
        "ticker": "ABT",
        "name": "애보트",
        "price": 106.09,
        "change": 0.04,
        "tier": 4,
        "rank": 309,
        "score": 4.2
      },
      {
        "ticker": "LMT",
        "name": "록히드 마틴",
        "price": 632.46,
        "change": 5.89,
        "tier": 4,
        "rank": 323,
        "score": 4.8
      },
      {
        "ticker": "ETN",
        "name": "이튼",
        "price": 353.17,
        "change": 1.68,
        "tier": 4,
        "rank": 331,
        "score": 4.0
      },
      {
        "ticker": "WDC",
        "name": "웨스턴 디지털",
        "price": 277.13,
        "change": -0.92,
        "tier": 4,
        "rank": 334,
        "score": 4.6
      },
      {
        "ticker": "IBM",
        "name": "IBM",
        "price": 311.77,
        "change": 5.98,
        "tier": 4,
        "rank": 336,
        "score": 4.8
      },
      {
        "ticker": "WDAY",
        "name": "워크데이",
        "price": 172.73,
        "change": -8.67,
        "tier": 4,
        "rank": 343,
        "score": 4.9
      },
      {
        "ticker": "AES",
        "name": "AES",
        "price": 14.9,
        "change": -1.88,
        "tier": 4,
        "rank": 346,
        "score": 4.1
      },
      {
        "ticker": "TYL",
        "name": "타일러 테크놀로지스",
        "price": 390.48,
        "change": -6.83,
        "tier": 4,
        "rank": 349,
        "score": 4.7
      },
      {
        "ticker": "VLO",
        "name": "발레로 에너지",
        "price": 190.57,
        "change": 3.56,
        "tier": 4,
        "rank": 352,
        "score": 4.6
      },
      {
        "ticker": "NOW",
        "name": "서비스나우",
        "price": 114.76,
        "change": -11.46,
        "tier": 4,
        "rank": 360,
        "score": 5.0
      },
      {
        "ticker": "PANW",
        "name": "팔로알토 네트웍스",
        "price": 172.62,
        "change": -6.05,
        "tier": 4,
        "rank": 365,
        "score": 4.4
      },
      {
        "ticker": "LUV",
        "name": "사우스웨스트 항공",
        "price": 47.21,
        "change": 15.53,
        "tier": 4,
        "rank": 372,
        "score": 4.9
      },
      {
        "ticker": "GLW",
        "name": "코닝",
        "price": 100.83,
        "change": -3.31,
        "tier": 4,
        "rank": 375,
        "score": 4.7
      },
      {
        "ticker": "RJF",
        "name": "레이먼드 제임스 파이낸셜",
        "price": 168.12,
        "change": -0.11,
        "tier": 4,
        "rank": 380,
        "score": 4.3
      },
      {
        "ticker": "HPQ",
        "name": "HP",
        "price": 19.56,
        "change": 2.68,
        "tier": 4,
        "rank": 387,
        "score": 4.1
      },
      {
        "ticker": "TXN",
        "name": "텍사스 인스트루먼츠",
        "price": 219.81,
        "change": 1.68,
        "tier": 4,
        "rank": 389,
        "score": 4.4
      },
      {
        "ticker": "FDS",
        "name": "팩트셋 리서치 시스템즈",
        "price": 255.23,
        "change": -5.42,
        "tier": 4,
        "rank": 396,
        "score": 4.2
      },
      {
        "ticker": "SHW",
        "name": "셔윈 윌리엄스",
        "price": 353.23,
        "change": 1.04,
        "tier": 4,
        "rank": 399,
        "score": 4.0
      },
      {
        "ticker": "IR",
        "name": "잉가솔 랜드",
        "price": 86.22,
        "change": 1.14,
        "tier": 5,
        "rank": 405,
        "score": 4.4
      },
      {
        "ticker": "CVX",
        "name": "셰브론",
        "price": 172.5,
        "change": 1.51,
        "tier": 5,
        "rank": 406,
        "score": 4.2
      },
      {
        "ticker": "SLB",
        "name": "슐럼버거",
        "price": 49.21,
        "change": 0.7,
        "tier": 5,
        "rank": 417,
        "score": 4.0
      },
      {
        "ticker": "SW",
        "name": "스머핏 웨스트록",
        "price": 41.85,
        "change": -1.32,
        "tier": 5,
        "rank": 445,
        "score": 4.3
      },
      {
        "ticker": "CRWD",
        "name": "크라우드스트라이크 홀딩스",
        "price": 438.73,
        "change": -6.49,
        "tier": 5,
        "rank": 447,
        "score": 4.8
      },
      {
        "ticker": "IP",
        "name": "인터내셔널 페이퍼",
        "price": 37.77,
        "change": -8.97,
        "tier": 5,
        "rank": 448,
        "score": 5.0
      },
      {
        "ticker": "OXY",
        "name": "옥시덴탈 페트롤리움",
        "price": 45.85,
        "change": 2.28,
        "tier": 5,
        "rank": 462,
        "score": 4.7
      },
      {
        "ticker": "BX",
        "name": "블랙스톤",
        "price": 141.94,
        "change": -3.3,
        "tier": 5,
        "rank": 463,
        "score": 4.4
      },
      {
        "ticker": "TSLA",
        "name": "테슬라",
        "price": 422.71,
        "change": -2.03,
        "tier": 5,
        "rank": 465,
        "score": 4.1
      },
      {
        "ticker": "DDOG",
        "name": "데이터독",
        "price": 129.86,
        "change": -7.61,
        "tier": 5,
        "rank": 469,
        "score": 4.5
      },
      {
        "ticker": "INTC",
        "name": "인텔",
        "price": 47.94,
        "change": -1.71,
        "tier": 5,
        "rank": 473,
        "score": 4.2
      },
      {
        "ticker": "DAY",
        "name": "데이포스",
        "price": 69.23,
        "change": -0.19,
        "tier": 5,
        "rank": 477,
        "score": 4.3
      },
      {
        "ticker": "AXON",
        "name": "액손 엔터프라이즈",
        "price": 514.84,
        "change": -6.37,
        "tier": 5,
        "rank": 482,
        "score": 4.2
      },
      {
        "ticker": "SBUX",
        "name": "스타벅스",
        "price": 94.08,
        "change": -1.13,
        "tier": 5,
        "rank": 493,
        "score": 4.3
      },
      {
        "ticker": "DOW",
        "name": "다우",
        "price": 26.81,
        "change": -3.49,
        "tier": 5,
        "rank": 494,
        "score": 4.8
      },
      {
        "ticker": "LYB",
        "name": "라이온델바젤 인더스트리스",
        "price": 49.74,
        "change": -1.45,
        "tier": 5,
        "rank": 500,
        "score": 4.0
      }
    ],
    "price_surge": [
      {
        "ticker": "CCL",
        "name": "카니발",
        "price": 30.84,
        "change": 7.38,
        "tier": 1,
        "rank": 19
      },
      {
        "ticker": "AOS",
        "name": "A O 스미스",
        "price": 73.96,
        "change": 6.44,
        "tier": 2,
        "rank": 61
      },
      {
        "ticker": "TT",
        "name": "트레인 테크놀로지스",
        "price": 426.78,
        "change": 8.26,
        "tier": 3,
        "rank": 144
      },
      {
        "ticker": "RCL",
        "name": "로얄 캐리비안 크루즈",
        "price": 335.17,
        "change": 14.94,
        "tier": 3,
        "rank": 180
      },
      {
        "ticker": "META",
        "name": "메타 플랫폼스(페이스북)",
        "price": 728.62,
        "change": 8.96,
        "tier": 3,
        "rank": 231
      },
      {
        "ticker": "NCLH",
        "name": "노르웨이지안 크루즈 라인 홀딩스",
        "price": 22.75,
        "change": 9.43,
        "tier": 3,
        "rank": 240
      },
      {
        "ticker": "LMT",
        "name": "록히드 마틴",
        "price": 632.46,
        "change": 5.89,
        "tier": 4,
        "rank": 323
      },
      {
        "ticker": "IBM",
        "name": "IBM",
        "price": 311.77,
        "change": 5.98,
        "tier": 4,
        "rank": 336
      },
      {
        "ticker": "LUV",
        "name": "사우스웨스트 항공",
        "price": 47.21,
        "change": 15.53,
        "tier": 4,
        "rank": 372
      }
    ],
    "price_plunge": [
      {
        "ticker": "FSLR",
        "name": "퍼스트 솔라",
        "price": 221.3,
        "change": -11.27,
        "tier": 1,
        "rank": 1
      },
      {
        "ticker": "NEM",
        "name": "뉴몬트",
        "price": 125.08,
        "change": -5.21,
        "tier": 1,
        "rank": 3
      },
      {
        "ticker": "LVS",
        "name": "라스베이거스 샌즈",
        "price": 52.72,
        "change": -13.94,
        "tier": 1,
        "rank": 4
      },
      {
        "ticker": "PTC",
        "name": "PTC",
        "price": 153.07,
        "change": -5.46,
        "tier": 1,
        "rank": 15
      },
      {
        "ticker": "MSFT",
        "name": "마이크로소프트",
        "price": 424.29,
        "change": -11.91,
        "tier": 2,
        "rank": 51
      },
      {
        "ticker": "URI",
        "name": "유나이티드 렌탈스",
        "price": 767.03,
        "change": -15.08,
        "tier": 3,
        "rank": 109
      },
      {
        "ticker": "CRM",
        "name": "세일즈포스",
        "price": 212.48,
        "change": -6.79,
        "tier": 3,
        "rank": 117
      },
      {
        "ticker": "ADSK",
        "name": "오토데스크",
        "price": 254.54,
        "change": -5.14,
        "tier": 3,
        "rank": 125
      },
      {
        "ticker": "INTU",
        "name": "인튜이트",
        "price": 496.2,
        "change": -7.89,
        "tier": 3,
        "rank": 139
      },
      {
        "ticker": "COIN",
        "name": "코인베이스",
        "price": 196.55,
        "change": -6.15,
        "tier": 3,
        "rank": 153
      },
      {
        "ticker": "TSCO",
        "name": "트랙터 서플라이",
        "price": 51.61,
        "change": -6.4,
        "tier": 4,
        "rank": 265
      },
      {
        "ticker": "CDNS",
        "name": "케이던스 디자인 시스템즈",
        "price": 298.95,
        "change": -6.72,
        "tier": 4,
        "rank": 276
      },
      {
        "ticker": "WDAY",
        "name": "워크데이",
        "price": 172.73,
        "change": -8.67,
        "tier": 4,
        "rank": 343
      },
      {
        "ticker": "TYL",
        "name": "타일러 테크놀로지스",
        "price": 390.48,
        "change": -6.83,
        "tier": 4,
        "rank": 349
      },
      {
        "ticker": "NOW",
        "name": "서비스나우",
        "price": 114.76,
        "change": -11.46,
        "tier": 4,
        "rank": 360
      },
      {
        "ticker": "PANW",
        "name": "팔로알토 네트웍스",
        "price": 172.62,
        "change": -6.05,
        "tier": 4,
        "rank": 365
      },
      {
        "ticker": "FDS",
        "name": "팩트셋 리서치 시스템즈",
        "price": 255.23,
        "change": -5.42,
        "tier": 4,
        "rank": 396
      },
      {
        "ticker": "SNPS",
        "name": "시놉시스",
        "price": 483.14,
        "change": -5.52,
        "tier": 5,
        "rank": 443
      },
      {
        "ticker": "CRWD",
        "name": "크라우드스트라이크 홀딩스",
        "price": 438.73,
        "change": -6.49,
        "tier": 5,
        "rank": 447
      },
      {
        "ticker": "IP",
        "name": "인터내셔널 페이퍼",
        "price": 37.77,
        "change": -8.97,
        "tier": 5,
        "rank": 448
      },
      {
        "ticker": "DDOG",
        "name": "데이터독",
        "price": 129.86,
        "change": -7.61,
        "tier": 5,
        "rank": 469
      },
      {
        "ticker": "AXON",
        "name": "액손 엔터프라이즈",
        "price": 514.84,
        "change": -6.37,
        "tier": 5,
        "rank": 482
      }
    ],
    "earnings_coming": [
      {
        "ticker": "AAPL",
        "name": "애플",
        "price": 255.86,
        "change": -0.23,
        "tier": 2,
        "rank": 37,
        "date": "2026-01-29",
        "d_day": 0
      },
      {
        "ticker": "DECK",
        "name": "데커스 아웃도어",
        "price": 98.95,
        "change": 1.36,
        "tier": 2,
        "rank": 60,
        "date": "2026-01-29",
        "d_day": 0
      },
      {
        "ticker": "AOS",
        "name": "A O 스미스",
        "price": 73.96,
        "change": 6.44,
        "tier": 2,
        "rank": 61,
        "date": "2026-01-29",
        "d_day": 0
      },
      {
        "ticker": "CMCSA",
        "name": "컴캐스트",
        "price": 29.46,
        "change": 3.7,
        "tier": 3,
        "rank": 108,
        "date": "2026-01-29",
        "d_day": 0
      },
      {
        "ticker": "DOV",
        "name": "도버",
        "price": 204.66,
        "change": -0.65,
        "tier": 3,
        "rank": 130,
        "date": "2026-01-29",
        "d_day": 0
      },
      {
        "ticker": "AON",
        "name": "에이온",
        "price": 341.78,
        "change": 2.64,
        "tier": 3,
        "rank": 189,
        "date": "2026-01-30",
        "d_day": 1
      },
      {
        "ticker": "AMP",
        "name": "아메리프라이즈 파이낸셜",
        "price": 523.94,
        "change": 4.86,
        "tier": 3,
        "rank": 199,
        "date": "2026-01-29",
        "d_day": 0
      },
      {
        "ticker": "CAT",
        "name": "캐터필러",
        "price": 669.58,
        "change": 4.09,
        "tier": 3,
        "rank": 226,
        "date": "2026-01-29",
        "d_day": 0
      },
      {
        "ticker": "CHTR",
        "name": "차터 커뮤니케이션스",
        "price": 188.24,
        "change": 2.97,
        "tier": 4,
        "rank": 264,
        "date": "2026-01-30",
        "d_day": 1
      },
      {
        "ticker": "AXP",
        "name": "아메리칸 익스프레스",
        "price": 358.48,
        "change": 0.42,
        "tier": 4,
        "rank": 306,
        "date": "2026-01-30",
        "d_day": 1
      },
      {
        "ticker": "CL",
        "name": "콜게이트 팜올리브",
        "price": 85.63,
        "change": 0.74,
        "tier": 4,
        "rank": 341,
        "date": "2026-01-30",
        "d_day": 1
      },
      {
        "ticker": "CVX",
        "name": "셰브론",
        "price": 172.5,
        "change": 1.51,
        "tier": 5,
        "rank": 406,
        "date": "2026-01-30",
        "d_day": 1
      },
      {
        "ticker": "BEN",
        "name": "프랭클린 리소시스",
        "price": 25.63,
        "change": -0.11,
        "tier": 5,
        "rank": 439,
        "date": "2026-01-30",
        "d_day": 1
      },
      {
        "ticker": "CHD",
        "name": "처치 앤드 드와이트",
        "price": 91.75,
        "change": 0.29,
        "tier": 5,
        "rank": 450,
        "date": "2026-01-30",
        "d_day": 1
      },
      {
        "ticker": "BX",
        "name": "블랙스톤",
        "price": 141.94,
        "change": -3.3,
        "tier": 5,
        "rank": 463,
        "date": "2026-01-29",
        "d_day": 0
      },
      {
        "ticker": "AJG",
        "name": "아서 J 갤러거",
        "price": 244.71,
        "change": 0.97,
        "tier": 5,
        "rank": 466,
        "date": "2026-01-29",
        "d_day": 0
      },
      {
        "ticker": "DOW",
        "name": "다우",
        "price": 26.81,
        "change": -3.49,
        "tier": 5,
        "rank": 494,
        "date": "2026-01-29",
        "d_day": 0
      },
      {
        "ticker": "APD",
        "name": "에어 프로덕츠 앤 케미컬스",
        "price": 255.98,
        "change": 0.03,
        "tier": 5,
        "rank": 498,
        "date": "2026-01-30",
        "d_day": 1
      }
    ],
    "dividend_ex": [
      {
        "ticker": "AOS",
        "name": "A O 스미스",
        "price": 73.96,
        "change": 6.44,
        "tier": 2,
        "rank": 61,
        "date": "2026-01-30",
        "d_day": 1,
        "yield": 1.98
      },
      {
        "ticker": "LNT",
        "name": "얼라이언트 에너지",
        "price": 66.33,
        "change": 0.11,
        "tier": 3,
        "rank": 202,
        "date": "2026-01-30",
        "d_day": 1,
        "yield": 3.06
      },
      {
        "ticker": "MS",
        "name": "모간 스탠리",
        "price": 180.62,
        "change": -0.94,
        "tier": 3,
        "rank": 206,
        "date": "2026-01-30",
        "d_day": 1,
        "yield": 2.19
      },
      {
        "ticker": "TRGP",
        "name": "타르가 리소시스",
        "price": 201.61,
        "change": 0.24,
        "tier": 3,
        "rank": 209,
        "date": "2026-01-30",
        "d_day": 1,
        "yield": 2.05
      },
      {
        "ticker": "FAST",
        "name": "패스널",
        "price": 43.51,
        "change": -0.24,
        "tier": 3,
        "rank": 242,
        "date": "2026-01-29",
        "d_day": 0,
        "yield": 2.05
      },
      {
        "ticker": "O",
        "name": "리얼티 인컴",
        "price": 60.48,
        "change": 0.68,
        "tier": 4,
        "rank": 287,
        "date": "2026-01-30",
        "d_day": 1,
        "yield": 5.32
      },
      {
        "ticker": "COST",
        "name": "코스트코",
        "price": 955.91,
        "change": -0.51,
        "tier": 4,
        "rank": 345,
        "date": "2026-01-30",
        "d_day": 1,
        "yield": 0.54
      },
      {
        "ticker": "AES",
        "name": "AES",
        "price": 14.9,
        "change": -1.88,
        "tier": 4,
        "rank": 346,
        "date": "2026-01-30",
        "d_day": 1,
        "yield": 4.72
      },
      {
        "ticker": "MRSH",
        "name": "마시 앤드 맥레넌",
        "price": 185.65,
        "change": 4.19,
        "tier": 4,
        "rank": 357,
        "date": "2026-01-29",
        "d_day": 0,
        "yield": 2.01
      },
      {
        "ticker": "TXN",
        "name": "텍사스 인스트루먼츠",
        "price": 219.81,
        "change": 1.68,
        "tier": 4,
        "rank": 389,
        "date": "2026-01-30",
        "d_day": 1,
        "yield": 2.89
      },
      {
        "ticker": "LW",
        "name": "램 웨스턴 홀딩스",
        "price": 45.83,
        "change": 0.8,
        "tier": 5,
        "rank": 432,
        "date": "2026-01-30",
        "d_day": 1,
        "yield": 3.37
      },
      {
        "ticker": "STZ",
        "name": "콘스텔레이션 브랜즈",
        "price": 153.74,
        "change": -2.54,
        "tier": 5,
        "rank": 459,
        "date": "2026-01-29",
        "d_day": 0,
        "yield": 2.53
      }
    ]
  }
}